substra/__init__.py
substra/__version__.py
substra/config.py
substra/sdk/__init__.py
substra/sdk/client.py
substra/sdk/compute_plan.py
substra/sdk/exceptions.py
substra/sdk/fs.py
substra/sdk/graph.py
substra/sdk/hasher.py
substra/sdk/models.py
substra/sdk/schemas.py
substra/sdk/utils.py
substra/sdk/archive/__init__.py
substra/sdk/archive/safezip.py
substra/sdk/archive/tarsafe.py
substra/sdk/backends/__init__.py
substra/sdk/backends/base.py
substra/sdk/backends/local/__init__.py
substra/sdk/backends/local/backend.py
substra/sdk/backends/local/dal.py
substra/sdk/backends/local/db.py
substra/sdk/backends/local/models.py
substra/sdk/backends/local/compute/__init__.py
substra/sdk/backends/local/compute/worker.py
substra/sdk/backends/local/compute/spawner/__init__.py
substra/sdk/backends/local/compute/spawner/base.py
substra/sdk/backends/local/compute/spawner/docker.py
substra/sdk/backends/local/compute/spawner/subprocess.py
substra/sdk/backends/remote/__init__.py
substra/sdk/backends/remote/backend.py
substra/sdk/backends/remote/request_formatter.py
substra/sdk/backends/remote/rest_client.py
substra-1.0.0.dist-info/METADATA
substra-1.0.0.dist-info/WHEEL
substra-1.0.0.dist-info/licenses/LICENSE
substra-1.0.0.dist-info/RECORD
