Metadata-Version: 2.3
Name: substra
Version: 1.0.0
Summary: Low-level Python library for interacting with a Substra network
Project-URL: Documentation, https://docs.substra.org/en/stable/
Project-URL: Repository, https://github.com/Substra/substra
Project-URL: Changelog, https://github.com/Substra/substra/blob/main/CHANGELOG.md
Author: Owkin, Inc.
License: 
License-File: LICENSE
Keywords: substra
Classifier: Intended Audience :: Developers
Classifier: Natural Language :: English
Classifier: Operating System :: OS Independent
Classifier: Programming Language :: Python :: 3.10
Classifier: Programming Language :: Python :: 3.11
Classifier: Programming Language :: Python :: 3.12
Classifier: Topic :: Utilities
Requires-Python: >=3.10
Requires-Dist: docker
Requires-Dist: pydantic<3.0.0,>=2.3.0
Requires-Dist: python-slugify
Requires-Dist: pyyaml
Requires-Dist: requests!=2.32.*
Requires-Dist: tqdm
Provides-Extra: dev
Requires-Dist: black; extra == 'dev'
Requires-Dist: docstring-parser; extra == 'dev'
Requires-Dist: flake8; extra == 'dev'
Requires-Dist: isort; extra == 'dev'
Requires-Dist: pandas; extra == 'dev'
Requires-Dist: pytest; extra == 'dev'
Requires-Dist: pytest-cov; extra == 'dev'
Requires-Dist: pytest-mock; extra == 'dev'
Requires-Dist: substratools~=1.0.0; extra == 'dev'
Requires-Dist: towncrier; extra == 'dev'
